Workbook

Sheet Attendance_Sheet
C3: Month | D3: Year | E3: ="Fully Automatic Attendance Sheet - "&C4&" "&D4 -> Fully Automatic Attendance Sheet - April 2026 | AJ3: DataMentix By Shoaib Saleem
C4: April | D4: 2026
C5: =DATEVALUE("1"&C4&D4) -> 46113 | D5: =EOMONTH(C5,0) -> 46142
C6: Emp_ID | D6: Emp_Name | E6: =C5 -> 46113 | F6: =IF(E6<$D$5,E6+1,"") -> 46114 | G6: =IF(F6<$D$5,F6+1,"") -> 46115 | H6: =IF(G6<$D$5,G6+1,"") -> 46116 | I6: =IF(H6<$D$5,H6+1,"") -> 46117 | J6: =IF(I6<$D$5,I6+1,"") -> 46118 | K6: =IF(J6<$D$5,J6+1,"") -> 46119 | L6: =IF(K6<$D$5,K6+1,"") -> 46120 | M6: =IF(L6<$D$5,L6+1,"") -> 46121 | ... AI6: =IF(AH6<$D$5,AH6+1,"") | AJ6: Total Days | AK6: Present | AL6: Holiday | AM6: Week Off | AN6: Absent
E7: =TEXT(E6,"ddd") -> Wed | F7: =TEXT(F6,"ddd") -> Thu | G7: =TEXT(G6,"ddd") -> Fri | H7: =TEXT(H6,"ddd") -> Sat | I7: =TEXT(I6,"ddd") -> Sun | J7: =TEXT(J6,"ddd") -> Mon | K7: =TEXT(K6,"ddd") -> Tue | L7: =TEXT(L6,"ddd") -> Wed | ... AI7: =TEXT(AI6,"ddd")
C9: EMP001 | D9: Aman Khan | E9: P | F9: P | G9: P | H9: P | J9: P | K9: P | L9: A | M9: P | N9: P | O9: P | Q9: P | R9: A | S9: P | T9: A | U9: P | V9: P | X9: P | Y9: P | AJ9: =COUNT(E$6:AI$6) -> 30 | AK9: =COUNTIF($E9:$AI9,"P") -> 15 | AL9: =COUNTIF($E9:$AI9,"H") -> 0 | AM9: =COUNTIF(E$7:AI$8,"Sun") -> 4 | AN9: =COUNTIF($E9:$AI9,"A") -> 3
C10: EMP002 | D10: Neha Sharma | E10: P | F10: P | G10: A | H10: P | J10: A | K10: P | L10: P | M10: P | N10: A | O10: P | Q10: A | R10: P | S10: A | T10: P | U10: P | V10: P | X10: P | Y10: P | AJ10: =COUNT(E$6:AI$6) -> 30 | AK10: =COUNTIF($E10:$AI10,"P") -> 13 | AL10: =COUNTIF($E10:$AI10,"H") -> 0 | AM10: =COUNTIF(E$7:AI$8,"Sun") -> 4 | AN10: =COUNTIF($E10:$AI10,"A") -> 5
C11: EMP003 | D11: Ali Raza | E11: A | F11: P | G11: P | H11: P | J11: P | K11: P | L11: A | M11: P | N11: P | O11: P | Q11: P | R11: P | S11: P | T11: P | U11: P | V11: A | X11: A | Y11: A | AJ11: =COUNT(E$6:AI$6) -> 30 | AK11: =COUNTIF($E11:$AI11,"P") -> 13 | AL11: =COUNTIF($E11:$AI11,"H") -> 0 | AM11: =COUNTIF(E$7:AI$8,"Sun") -> 4 | AN11: =COUNTIF($E11:$AI11,"A") -> 5
C12: EMP004 | D12: Riya Singh | E12: P | F12: P | G12: P | H12: P | J12: P | K12: P | L12: P | M12: A | N12: P | O12: P | Q12: P | R12: A | S12: P | T12: A | U12: P | V12: P | X12: P | Y12: P | AJ12: =COUNT(E$6:AI$6) -> 30 | AK12: =COUNTIF($E12:$AI12,"P") -> 15 | AL12: =COUNTIF($E12:$AI12,"H") -> 0 | AM12: =COUNTIF(E$7:AI$8,"Sun") -> 4 | AN12: =COUNTIF($E12:$AI12,"A") -> 3 | BF12: sfdsfs
C13: EMP005 | D13: Shah Alam | E13: P | F13: P | G13: A | H13: P | J13: P | K13: P | L13: P | M13: P | N13: P | O13: A | Q13: A | R13: P | S13: P | T13: P | U13: A | V13: P | X13: P | Y13: P | AJ13: =COUNT(E$6:AI$6) -> 30 | AK13: =COUNTIF($E13:$AI13,"P") -> 14 | AL13: =COUNTIF($E13:$AI13,"H") -> 0 | AM13: =COUNTIF(E$7:AI$8,"Sun") -> 4 | AN13: =COUNTIF($E13:$AI13,"A") -> 4
C14: EMP006 | D14: Karan Gupta | E14: P | F14: A | G14: P | H14: P | J14: P | K14: A | L14: P | M14: A | N14: P | O14: P | Q14: P | R14: P | S14: A | T14: P | U14: P | V14: P | X14: P | Y14: P | AJ14: =COUNT(E$6:AI$6) -> 30 | AK14: =COUNTIF($E14:$AI14,"P") -> 14 | AL14: =COUNTIF($E14:$AI14,"H") -> 0 | AM14: =COUNTIF(E$7:AI$8,"Sun") -> 4 | AN14: =COUNTIF($E14:$AI14,"A") -> 4
C15: EMP007 | D15: Irfan Pathan | E15: A | F15: P | G15: P | H15: A | J15: P | K15: P | L15: P | M15: P | N15: P | O15: A | Q15: P | R15: P | S15: P | T15: P | U15: P | V15: A | X15: A | Y15: A | AJ15: =COUNT(E$6:AI$6) -> 30 | AK15: =COUNTIF($E15:$AI15,"P") -> 12 | AL15: =COUNTIF($E15:$AI15,"H") -> 0 | AM15: =COUNTIF(E$7:AI$8,"Sun") -> 4 | AN15: =COUNTIF($E15:$AI15,"A") -> 6
C16: EMP008 | D16: Pappi Singh | E16: P | F16: P | G16: P | H16: P | J16: A | K16: P | L16: A | M16: P | N16: A | O16: P | Q16: P | R16: A | S16: P | T16: A | U16: P | V16: P | X16: P | Y16: P | AJ16: =COUNT(E$6:AI$6) -> 30 | AK16: =COUNTIF($E16:$AI16,"P") -> 13 | AL16: =COUNTIF($E16:$AI16,"H") -> 0 | AM16: =COUNTIF(E$7:AI$8,"Sun") -> 4 | AN16: =COUNTIF($E16:$AI16,"A") -> 5
C17: EMP009 | D17: Raju Roi | E17: P | F17: A | G17: P | H17: P | J17: P | K17: P | L17: P | M17: P | N17: P | O17: A | Q17: P | R17: P | S17: P | T17: P | U17: A | V17: P | X17: P | Y17: P | AJ17: =COUNT(E$6:AI$6) -> 30 | AK17: =COUNTIF($E17:$AI17,"P") -> 15 | AL17: =COUNTIF($E17:$AI17,"H") -> 0 | AM17: =COUNTIF(E$7:AI$8,"Sun") -> 4 | AN17: =COUNTIF($E17:$AI17,"A") -> 3
C18: EMP010 | D18: Rabia Ansari | E18: P | F18: P | G18: A | H18: P | J18: P | K18: A | L18: P | M18: A | N18: P | O18: P | Q18: A | R18: P | S18: A | T18: P | U18: P | V18: A | X18: A | Y18: A | AJ18: =COUNT(E$6:AI$6) -> 30 | AK18: =COUNTIF($E18:$AI18,"P") -> 10 | AL18: =COUNTIF($E18:$AI18,"H") -> 0 | AM18: =COUNTIF(E$7:AI$8,"Sun") -> 4 | AN18: =COUNTIF($E18:$AI18,"A") -> 8
C19: EMP011 | D19: Ram Kumar | E19: P | F19: A | G19: P | H19: P | J19: P | K19: P | L19: P | M19: P | N19: P | O19: P | Q19: P | R19: P | S19: P | T19: P | U19: P | V19: P | X19: P | Y19: P | AJ19: =COUNT(E$6:AI$6) -> 30 | AK19: =COUNTIF($E19:$AI19,"P") -> 17 | AL19: =COUNTIF($E19:$AI19,"H") -> 0 | AM19: =COUNTIF(E$7:AI$8,"Sun") -> 4 | AN19: =COUNTIF($E19:$AI19,"A") -> 1
C20: EMP012 | D20: Raja Babu | E20: A | F20: P | G20: P | H20: P | J20: P | K20: P | L20: A | M20: P | N20: P | O20: A | Q20: P | R20: A | S20: P | T20: P | U20: A | V20: P | X20: P | Y20: P | AJ20: =COUNT(E$6:AI$6) -> 30 | AK20: =COUNTIF($E20:$AI20,"P") -> 13 | AL20: =COUNTIF($E20:$AI20,"H") -> 0 | AM20: =COUNTIF(E$7:AI$8,"Sun") -> 4 | AN20: =COUNTIF($E20:$AI20,"A") -> 5
C21: EMP013 | D21: Fiza Khan | E21: P | F21: P | G21: A | H21: P | J21: A | K21: P | L21: P | M21: P | N21: P | O21: P | Q21: P | R21: P | S21: P | T21: A | U21: P | V21: P | X21: P | Y21: P | AJ21: =COUNT(E$6:AI$6) -> 30 | AK21: =COUNTIF($E21:$AI21,"P") -> 15 | AL21: =COUNTIF($E21:$AI21,"H") -> 0 | AM21: =COUNTIF(E$7:AI$8,"Sun") -> 4 | AN21: =COUNTIF($E21:$AI21,"A") -> 3
C27: January
C28: February
C29: March
C30: April
C31: May
C32: June
C33: July
C34: August
C35: September
C36: October
C37: November
C38: December

Sheet Salary_Sheet
A1: ="Fully Automatic Salary Sheet - "&Attendance_Sheet!C4&" "&Attendance_Sheet!D4 -> Fully Automatic Salary Sheet - April 2026 | P1: DataMentix By Shoaib Saleem
A4: Emp_ID | B4: EMP_Name | C4: Designation | D4: Basic Salary | E4: Total Days | F4: Attendance(Working Days) | G4: Per Day Salary | H4: Salary (Based on Attendance) | I4: DA (12%) | J4: City | K4: HRA | L4: TA | M4: OT in Hrs. | N4: Overtime Pay | O4: Gross Salary | P4: PF (12%) | Q4: ESI (0.75%) | R4: Net Salary
A5: =VLOOKUP(Attendance_Sheet!C9,Attendance_Sheet!C6:D21,1,FALSE) -> EMP001 | B5: =VLOOKUP(A5,Attendance_Sheet!C6:D21,2,FALSE) -> Aman Khan | C5: Manager | D5: 30000 | E5: =VLOOKUP(A5,Attendance_Sheet!C6:AN21,34,FALSE) -> 30 | F5: =SUMPRODUCT(VLOOKUP(A5,Attendance_Sheet!C6:AN21,{35,36,37},FALSE)) -> 19 | G5: =D5/E5 -> 1000 | H5: =F5*G5 -> 19000 | I5: =D5*12% -> 3600 | J5: Metro | K5: =IF(J5="Metro",D5*50%,D5*40%) -> 15000 | L5: 1000 | M5: 10 | N5: =G5/8*M5 -> 1250 | O5: =H5+I5+K5+L5+N5 -> 39850 | P5: =D5*12% -> 3600 | Q5: =IF(O5<=21000,O5*0.75%,"N/A") -> N/A | R5: =IF(ISNUMBER(Q5),O5-P5-Q5,O5-P5) -> 36250
A6: =VLOOKUP(Attendance_Sheet!C10,Attendance_Sheet!C7:D22,1,FALSE) -> EMP002 | B6: =VLOOKUP(A6,Attendance_Sheet!C7:D22,2,FALSE) -> Neha Sharma | C6: Engineer | D6: 25000 | E6: =VLOOKUP(A6,Attendance_Sheet!C7:AN22,34,FALSE) -> 30 | F6: =SUMPRODUCT(VLOOKUP(A6,Attendance_Sheet!C7:AN22,{35,36,37},FALSE)) -> 17 | G6: =D6/E6 -> 833.33333 | H6: =F6*G6 -> 14166.667 | I6: =D6*12% -> 3000 | J6: Non-Metro | K6: =IF(J6="Metro",D6*50%,D6*40%) -> 10000 | L6: 2000 | M6: 15 | N6: =G6/8*M6 -> 1562.5 | O6: =H6+I6+K6+L6+N6 -> 30729.167 | P6: =D6*12% -> 3000 | Q6: =IF(O6<=21000,O6*0.75%,"N/A") -> N/A | R6: =IF(ISNUMBER(Q6),O6-P6-Q6,O6-P6) -> 27729.167
A7: =VLOOKUP(Attendance_Sheet!C11,Attendance_Sheet!C8:D23,1,FALSE) -> EMP003 | B7: =VLOOKUP(A7,Attendance_Sheet!C8:D23,2,FALSE) -> Ali Raza | C7: Supervisor | D7: 18000 | E7: =VLOOKUP(A7,Attendance_Sheet!C8:AN23,34,FALSE) -> 30 | F7: =SUMPRODUCT(VLOOKUP(A7,Attendance_Sheet!C8:AN23,{35,36,37},FALSE)) -> 17 | G7: =D7/E7 -> 600 | H7: =F7*G7 -> 10200 | I7: =D7*12% -> 2160 | J7: Metro | K7: =IF(J7="Metro",D7*50%,D7*40%) -> 9000 | L7: 1000 | M7: 20 | N7: =G7/8*M7 -> 1500 | O7: =H7+I7+K7+L7+N7 -> 23860 | P7: =D7*12% -> 2160 | Q7: =IF(O7<=21000,O7*0.75%,"N/A") -> N/A | R7: =IF(ISNUMBER(Q7),O7-P7-Q7,O7-P7) -> 21700
A8: =VLOOKUP(Attendance_Sheet!C12,Attendance_Sheet!C9:D24,1,FALSE) -> EMP004 | B8: =VLOOKUP(A8,Attendance_Sheet!C9:D24,2,FALSE) -> Riya Singh | C8: S. Tech | D8: 15000 | E8: =VLOOKUP(A8,Attendance_Sheet!C9:AN24,34,FALSE) -> 30 | F8: =SUMPRODUCT(VLOOKUP(A8,Attendance_Sheet!C9:AN24,{35,36,37},FALSE)) -> 19 | G8: =D8/E8 -> 500 | H8: =F8*G8 -> 9500 | I8: =D8*12% -> 1800 | J8: Metro | K8: =IF(J8="Metro",D8*50%,D8*40%) -> 7500 | L8: 3000 | M8: 25 | N8: =G8/8*M8 -> 1562.5 | O8: =H8+I8+K8+L8+N8 -> 23362.5 | P8: =D8*12% -> 1800 | Q8: =IF(O8<=21000,O8*0.75%,"N/A") -> N/A | R8: =IF(ISNUMBER(Q8),O8-P8-Q8,O8-P8) -> 21562.5
A9: =VLOOKUP(Attendance_Sheet!C13,Attendance_Sheet!C10:D25,1,FALSE) -> EMP005 | B9: =VLOOKUP(A9,Attendance_Sheet!C10:D25,2,FALSE) -> Shah Alam | C9: S. Tech | D9: 15000 | E9: =VLOOKUP(A9,Attendance_Sheet!C10:AN25,34,FALSE) -> 30 | F9: =SUMPRODUCT(VLOOKUP(A9,Attendance_Sheet!C10:AN25,{35,36,37},FALSE)) -> 18 | G9: =D9/E9 -> 500 | H9: =F9*G9 -> 9000 | I9: =D9*12% -> 1800 | J9: Non-Metro | K9: =IF(J9="Metro",D9*50%,D9*40%) -> 6000 | L9: 2000 | M9: 20 | N9: =G9/8*M9 -> 1250 | O9: =H9+I9+K9+L9+N9 -> 20050 | P9: =D9*12% -> 1800 | Q9: =IF(O9<=21000,O9*0.75%,"N/A") -> 150.375 | R9: =IF(ISNUMBER(Q9),O9-P9-Q9,O9-P9) -> 18099.625
A10: =VLOOKUP(Attendance_Sheet!C14,Attendance_Sheet!C11:D26,1,FALSE) -> EMP006 | B10: =VLOOKUP(A10,Attendance_Sheet!C11:D26,2,FALSE) -> Karan Gupta | C10: S. Tech | D10: 15000 | E10: =VLOOKUP(A10,Attendance_Sheet!C11:AN26,34,FALSE) -> 30 | F10: =SUMPRODUCT(VLOOKUP(A10,Attendance_Sheet!C11:AN26,{35,36,37},FALSE)) -> 18 | G10: =D10/E10 -> 500 | H10: =F10*G10 -> 9000 | I10: =D10*12% -> 1800 | J10: Non-Metro | K10: =IF(J10="Metro",D10*50%,D10*40%) -> 6000 | L10: 1000 | M10: 12 | N10: =G10/8*M10 -> 750 | O10: =H10+I10+K10+L10+N10 -> 18550 | P10: =D10*12% -> 1800 | Q10: =IF(O10<=21000,O10*0.75%,"N/A") -> 139.125 | R10: =IF(ISNUMBER(Q10),O10-P10-Q10,O10-P10) -> 16610.875
A11: =VLOOKUP(Attendance_Sheet!C15,Attendance_Sheet!C12:D27,1,FALSE) -> EMP007 | B11: =VLOOKUP(A11,Attendance_Sheet!C12:D27,2,FALSE) -> Irfan Pathan | C11: Tech | D11: 12000 | E11: =VLOOKUP(A11,Attendance_Sheet!C12:AN27,34,FALSE) -> 30 | F11: =SUMPRODUCT(VLOOKUP(A11,Attendance_Sheet!C12:AN27,{35,36,37},FALSE)) -> 16 | G11: =D11/E11 -> 400 | H11: =F11*G11 -> 6400 | I11: =D11*12% -> 1440 | J11: Metro | K11: =IF(J11="Metro",D11*50%,D11*40%) -> 6000 | L11: 3000 | M11: 15 | N11: =G11/8*M11 -> 750 | O11: =H11+I11+K11+L11+N11 -> 17590 | P11: =D11*12% -> 1440 | Q11: =IF(O11<=21000,O11*0.75%,"N/A") -> 131.925 | R11: =IF(ISNUMBER(Q11),O11-P11-Q11,O11-P11) -> 16018.075
A12: =VLOOKUP(Attendance_Sheet!C16,Attendance_Sheet!C13:D28,1,FALSE) -> EMP008 | B12: =VLOOKUP(A12,Attendance_Sheet!C13:D28,2,FALSE) -> Pappi Singh | C12: Tech | D12: 12000 | E12: =VLOOKUP(A12,Attendance_Sheet!C13:AN28,34,FALSE) -> 30 | F12: =SUMPRODUCT(VLOOKUP(A12,Attendance_Sheet!C13:AN28,{35,36,37},FALSE)) -> 17 | G12: =D12/E12 -> 400 | H12: =F12*G12 -> 6800 | I12: =D12*12% -> 1440 | J12: Non-Metro | K12: =IF(J12="Metro",D12*50%,D12*40%) -> 4800 | L12: 2000 | M12: 25 | N12: =G12/8*M12 -> 1250 | O12: =H12+I12+K12+L12+N12 -> 16290 | P12: =D12*12% -> 1440 | Q12: =IF(O12<=21000,O12*0.75%,"N/A") -> 122.175 | R12: =IF(ISNUMBER(Q12),O12-P12-Q12,O12-P12) -> 14727.825
A13: =VLOOKUP(Attendance_Sheet!C17,Attendance_Sheet!C14:D29,1,FALSE) -> EMP009 | B13: =VLOOKUP(A13,Attendance_Sheet!C14:D29,2,FALSE) -> Raju Roi | C13: Tech | D13: 12000 | E13: =VLOOKUP(A13,Attendance_Sheet!C14:AN29,34,FALSE) -> 30 | F13: =SUMPRODUCT(VLOOKUP(A13,Attendance_Sheet!C14:AN29,{35,36,37},FALSE)) -> 19 | G13: =D13/E13 -> 400 | H13: =F13*G13 -> 7600 | I13: =D13*12% -> 1440 | J13: Metro | K13: =IF(J13="Metro",D13*50%,D13*40%) -> 6000 | L13: 1000 | M13: 20 | N13: =G13/8*M13 -> 1000 | O13: =H13+I13+K13+L13+N13 -> 17040 | P13: =D13*12% -> 1440 | Q13: =IF(O13<=21000,O13*0.75%,"N/A") -> 127.8 | R13: =IF(ISNUMBER(Q13),O13-P13-Q13,O13-P13) -> 15472.2
A14: =VLOOKUP(Attendance_Sheet!C18,Attendance_Sheet!C15:D30,1,FALSE) -> EMP010 | B14: =VLOOKUP(A14,Attendance_Sheet!C15:D30,2,FALSE) -> Rabia Ansari | C14: Tech | D14: 12000 | E14: =VLOOKUP(A14,Attendance_Sheet!C15:AN30,34,FALSE) -> 30 | F14: =SUMPRODUCT(VLOOKUP(A14,Attendance_Sheet!C15:AN30,{35,36,37},FALSE)) -> 14 | G14: =D14/E14 -> 400 | H14: =F14*G14 -> 5600 | I14: =D14*12% -> 1440 | J14: Metro | K14: =IF(J14="Metro",D14*50%,D14*40%) -> 6000 | L14: 1000 | M14: 10 | N14: =G14/8*M14 -> 500 | O14: =H14+I14+K14+L14+N14 -> 14540 | P14: =D14*12% -> 1440 | Q14: =IF(O14<=21000,O14*0.75%,"N/A") -> 109.05 | R14: =IF(ISNUMBER(Q14),O14-P14-Q14,O14-P14) -> 12990.95
A15: =VLOOKUP(Attendance_Sheet!C19,Attendance_Sheet!C16:D31,1,FALSE) -> EMP011 | B15: =VLOOKUP(A15,Attendance_Sheet!C16:D31,2,FALSE) -> Ram Kumar | C15: Helper | D15: 10000 | E15: =VLOOKUP(A15,Attendance_Sheet!C16:AN31,34,FALSE) -> 30 | F15: =SUMPRODUCT(VLOOKUP(A15,Attendance_Sheet!C16:AN31,{35,36,37},FALSE)) -> 21 | G15: =D15/E15 -> 333.33333 | H15: =F15*G15 -> 7000 | I15: =D15*12% -> 1200 | J15: Metro | K15: =IF(J15="Metro",D15*50%,D15*40%) -> 5000 | L15: 2000 | M15: 22 | N15: =G15/8*M15 -> 916.66667 | O15: =H15+I15+K15+L15+N15 -> 16116.667 | P15: =D15*12% -> 1200 | Q15: =IF(O15<=21000,O15*0.75%,"N/A") -> 120.875 | R15: =IF(ISNUMBER(Q15),O15-P15-Q15,O15-P15) -> 14795.792
A16: =VLOOKUP(Attendance_Sheet!C20,Attendance_Sheet!C17:D32,1,FALSE) -> EMP012 | B16: =VLOOKUP(A16,Attendance_Sheet!C17:D32,2,FALSE) -> Raja Babu | C16: Helper | D16: 10000 | E16: =VLOOKUP(A16,Attendance_Sheet!C17:AN32,34,FALSE) -> 30 | F16: =SUMPRODUCT(VLOOKUP(A16,Attendance_Sheet!C17:AN32,{35,36,37},FALSE)) -> 17 | G16: =D16/E16 -> 333.33333 | H16: =F16*G16 -> 5666.6667 | I16: =D16*12% -> 1200 | J16: Non-Metro | K16: =IF(J16="Metro",D16*50%,D16*40%) -> 4000 | L16: 2000 | M16: 23 | N16: =G16/8*M16 -> 958.33333 | O16: =H16+I16+K16+L16+N16 -> 13825 | P16: =D16*12% -> 1200 | Q16: =IF(O16<=21000,O16*0.75%,"N/A") -> 103.6875 | R16: =IF(ISNUMBER(Q16),O16-P16-Q16,O16-P16) -> 12521.312
A17: =VLOOKUP(Attendance_Sheet!C21,Attendance_Sheet!C18:D33,1,FALSE) -> EMP013 | B17: =VLOOKUP(A17,Attendance_Sheet!C18:D33,2,FALSE) -> Fiza Khan | C17: Helper | D17: 10000 | E17: =VLOOKUP(A17,Attendance_Sheet!C18:AN33,34,FALSE) -> 30 | F17: =SUMPRODUCT(VLOOKUP(A17,Attendance_Sheet!C18:AN33,{35,36,37},FALSE)) -> 19 | G17: =D17/E17 -> 333.33333 | H17: =F17*G17 -> 6333.3333 | I17: =D17*12% -> 1200 | J17: Metro | K17: =IF(J17="Metro",D17*50%,D17*40%) -> 5000 | L17: 3000 | M17: 15 | N17: =G17/8*M17 -> 625 | O17: =H17+I17+K17+L17+N17 -> 16158.333 | P17: =D17*12% -> 1200 | Q17: =IF(O17<=21000,O17*0.75%,"N/A") -> 121.1875 | R17: =IF(ISNUMBER(Q17),O17-P17-Q17,O17-P17) -> 14837.146

Sheet Salary_Slip
B2: DataMentix Services Private Limited
C3: Prepared By Shoaib Saleem
C4: New Friends Colony, South East Delhi, India-110025
C5: ="Salary Slip For The Month Of - "&Attendance_Sheet!C4&" "&Attendance_Sheet!D4 -> Salary Slip For The Month Of - April 2026
C7: Employee Details | E7: Salary Details
C8: Emp_ID | D8: EMP001 | E8: Total Days | F8: =VLOOKUP($D$8,Salary_Sheet!$A$4:$R$17,MATCH(E8,Salary_Sheet!$A$4:$R$4,0),FALSE) -> 30
C9: Emp_Name | D9: =VLOOKUP($D$8,Salary_Sheet!$A$4:$R$17,MATCH(C9,Salary_Sheet!$A$4:$R$4,0),FALSE) -> Aman Khan | E9: Attendance(Working Days) | F9: =VLOOKUP($D$8,Salary_Sheet!$A$4:$R$17,MATCH(E9,Salary_Sheet!$A$4:$R$4,0),FALSE) -> 19
C10: Designation | D10: =VLOOKUP($D$8,Salary_Sheet!$A$4:$R$17,3,FALSE) -> Manager | E10: Salary Slip Print Date | F10: =TODAY() -> 46166
C12: Basic Salary | E12: =VLOOKUP($D$8,Salary_Sheet!$A$4:$R$17,MATCH(C12,Salary_Sheet!$A$4:$R$4,0),FALSE) -> 30000
C14: Earnings | E14: Deductions
C15: Salary (Based on Attendance) | D15: =VLOOKUP($D$8,Salary_Sheet!$A$4:$R$17,MATCH(C15,Salary_Sheet!$A$4:$R$4,0),FALSE) -> 19000 | E15: PF (12%) | F15: =VLOOKUP($D$8,Salary_Sheet!$A$4:$R$17,MATCH(E15,Salary_Sheet!$A$4:$R$4,0),FALSE) -> 3600
C16: DA (12%) | D16: =VLOOKUP($D$8,Salary_Sheet!$A$4:$R$17,MATCH(C16,Salary_Sheet!$A$4:$R$4,0),FALSE) -> 3600 | E16: ESI (0.75%) | F16: =VLOOKUP($D$8,Salary_Sheet!$A$4:$R$17,MATCH(E16,Salary_Sheet!$A$4:$R$4,0),FALSE) -> N/A
C17: HRA | D17: =VLOOKUP($D$8,Salary_Sheet!$A$4:$R$17,MATCH(C17,Salary_Sheet!$A$4:$R$4,0),FALSE) -> 15000 | E17: Loan | F17: =IFERROR(VLOOKUP($D$8,Salary_Sheet!$A$4:$R$17,MATCH(E17,Salary_Sheet!$A$4:$R$4,0),FALSE),0) -> 0
C18: TA | D18: =VLOOKUP($D$8,Salary_Sheet!$A$4:$R$17,MATCH(C18,Salary_Sheet!$A$4:$R$4,0),FALSE) -> 1000 | E18: Tax | F18: =IFERROR(VLOOKUP($D$8,Salary_Sheet!$A$4:$R$17,MATCH(E18,Salary_Sheet!$A$4:$R$4,0),FALSE),0) -> 0
C19: Overtime Pay | D19: =VLOOKUP($D$8,Salary_Sheet!$A$4:$R$17,MATCH(C19,Salary_Sheet!$A$4:$R$4,0),FALSE) -> 1250
C20: Gross Salary | D20: =SUM(D15:D19) -> 39850 | E20: Gross Deduction | F20: =SUM(F15:F18) -> 3600
C22: Net Salary | E22: =D20-F20 -> 36250
C24: Employee Signature | E24: Manager Signature
C26: This is a sample salary slip generated for educational purpose.
